MANIFEST.in
README.rst
buildout.cfg
develop.cfg
requirements.txt
setup.py
version.txt
bob/__init__.py
bob.db.msu_mfsd_mod.egg-info/PKG-INFO
bob.db.msu_mfsd_mod.egg-info/SOURCES.txt
bob.db.msu_mfsd_mod.egg-info/dependency_links.txt
bob.db.msu_mfsd_mod.egg-info/entry_points.txt
bob.db.msu_mfsd_mod.egg-info/not-zip-safe
bob.db.msu_mfsd_mod.egg-info/requires.txt
bob.db.msu_mfsd_mod.egg-info/top_level.txt
bob/db/__init__.py
bob/db/msu_mfsd_mod/__init__.py
bob/db/msu_mfsd_mod/create.py
bob/db/msu_mfsd_mod/driver.py
bob/db/msu_mfsd_mod/models.py
bob/db/msu_mfsd_mod/query.py
bob/db/msu_mfsd_mod/test.py
bob/db/msu_mfsd_mod/testme.py
bob/db/msu_mfsd_mod/verificationprotocol.py
bob/db/msu_mfsd_mod/folds/clients_fold1.txt
bob/db/msu_mfsd_mod/folds/clients_fold2.txt
bob/db/msu_mfsd_mod/folds/clients_fold3.txt
bob/db/msu_mfsd_mod/folds/clients_fold4.txt
bob/db/msu_mfsd_mod/folds/clients_fold5.txt
bob/db/msu_mfsd_mod/folds/msu_mfsd_mod_attackvids.txt
bob/db/msu_mfsd_mod/folds/msu_mfsd_mod_realvids.txt
bob/db/msu_mfsd_mod/folds/test_clients.txt
bob/db/msu_mfsd_mod/folds/test_sub_list.txt
bob/db/msu_mfsd_mod/folds/train_clients_1.txt
bob/db/msu_mfsd_mod/folds/train_clients_2.txt
bob/db/msu_mfsd_mod/folds/train_clients_3.txt
bob/db/msu_mfsd_mod/folds/train_clients_4.txt
bob/db/msu_mfsd_mod/folds/train_clients_5.txt
bob/db/msu_mfsd_mod/folds/train_sub_list.txt
bob/db/msu_mfsd_mod/rotated_videos/rotated_videos.txt
bob/db/msu_mfsd_mod/test_images/real_client005_android_SD_scene01_frame0_correct.hdf5
bob/db/msu_mfsd_mod/test_images/real_client022_android_SD_scene01_frame0_correct.hdf5
bob/db/msu_mfsd_mod/test_images/real/real_client005_android_SD_scene01.mp4
bob/db/msu_mfsd_mod/test_images/real/real_client022_android_SD_scene01.mp4
doc/conf.py
doc/guide.rst
doc/index.rst
doc/py_api.rst