Metadata-Version: 1.1
Name: bob.db.msu-mfsd-mod
Version: 2.2.4
Summary: MSU Mobile Face Spoofing Database Access API for Bob, with modified protocol
Home-page: http://gitlab.idiap.ch/bob/bob.db.msu_mfsd_mod
Author: Ivana Chingovska, Sushil Bhattacharjee
Author-email: ivana.chingovska@idiap.ch, sushil.bhattacharjee@idiap.ch
License: BSD
Platform: UNKNOWN
Classifier: Framework :: Bob
Classifier: Development Status :: 4 - Beta
Classifier: Intended Audience :: Science/Research
Classifier: License :: OSI Approved :: BSD License
Classifier: Natural Language :: English
Classifier: Programming Language :: Python
Classifier: Programming Language :: Python :: 3
Classifier: Topic :: Scientific/Engineering :: Artificial Intelligence
Classifier: Topic :: Database :: Front-Ends
